{
    "CompanyName": [
        "会社名",
        "トヨタ自動車株式会社",
        "－"
    ],
    "Sales": [
        "売上高(IFRS)",
        45095325000000,
        "円"
    ],
    "OperatingProfits": [
        "営業利益(IFRS)",
        5352934000000,
        "円"
    ],
    "NetIncome": [
        "当期純利益(IFRS)",
        4944933000000,
        "円"
    ],
    "Assets": [
        "資産(IFRS)",
        90114296000000,
        "円"
    ],
    "Liabilities": [
        "負債(IFRS)",
        54874958000000,
        "円"
    ],
    "CurrentAssets": [
        "流動資産(IFRS)",
        34714279000000,
        "円"
    ],
    "NonCurrentAssets": [
        "固定資産(IFRS)",
        55400017000000,
        "円"
    ],
    "EndDate": [
        "当会計期間終了日",
        "2024-03-31",
        "－"
    ],
    "NetAssets": [
        "資本(IFRS)",
        35239338000000,
        "円"
    ],
    "CurrentLiabilities": [
        "流動負債(IFRS)",
        29177909000000,
        "円"
    ],
    "NonCurrentLiabilities": [
        "固定負債(IFRS)",
        25697049000000,
        "円"
    ],
    "Interest-bearingCurrentLiabilities": [
        "有利子流動負債(IFRS)",
        15406284000000,
        "円"
    ],
    "Interest-bearingNonCurrentLiabilities": [
        "有利子固定負債(IFRS)",
        21155496000000,
        "円"
    ]
}